tmpnn/__init__.py
tmpnn/_triplet_loss.py
tmpnn/_utils.py
tmpnn/base.py
tmpnn/models.py
tmpnn-0.0.3.dist-info/LICENSE
tmpnn-0.0.3.dist-info/METADATA
tmpnn-0.0.3.dist-info/WHEEL
tmpnn-0.0.3.dist-info/top_level.txt
tmpnn-0.0.3.dist-info/RECORD
