Metadata-Version: 2.1
Name: tmpnn
Version: 0.0.3
Summary: Iimplementation of TMPNN, tabular polynomial network.
Home-page: https://github.com/andiva/tmpnn
Author: Stefan Maria Ailuro
Author-email: ailuro.sm@gmail.com
Classifier: Programming Language :: Python :: 3
Classifier: License :: OSI Approved :: MIT License
Classifier: Operating System :: OS Independent
Requires-Python: >3.8
License-File: LICENSE
Requires-Dist: tensorflow
Requires-Dist: scipy
Requires-Dist: scikit-learn
